{
  "items": [
    {
      "id": 29756,
      "examenId": 988,
      "usuarioId": 1217,
      "studentId": 1068,
      "numeroLegajo": 972023,
      "numeroDocumento": null,
      "nombre": null,
      "apellido": null,
      "malla": "Malla Informática 2015",
      "anioInscripcion": null,
      "codMateria": "318",
      "materia": "Redes de Computadoras I",
      "carrera": "Informática",
      "semestre": 4,
      "fechaExamen": "2025-06-27T17:30:00",
      "fechaLimiteInscripcionExamen": "2025-06-25T10:00:00",
      "fechaInscripcionMateria": "2025-02-19T10:38:56.8418201",
      "fechaInscripcion": "0001-01-01T00:00:00",
      "usuarioInscripcion": null,
      "porcentajeAsistencia": 90,
      "porcentajePP": 81,
      "porcentajePF": 0,
      "porcentajePC": 0,
      "calificacion": null,
      "calificacionText": null,
      "esInconsistente": false,
      "asistenciaMateria": 0,
      "ppMateria": 0,
      "inscripto": false,
      "esRecuperatorio": false,
      "instancia": {
        "value": 0,
        "label": "Final",
        "parentId": 0,
        "item": {
          "asis": true,
          "pp": true,
          "motivo": "PP > 49"
        }
      },
      "estadoExamen": null
    },
    {
      "id": 29760,
      "examenId": 990,
      "usuarioId": 1217,
      "studentId": 1068,
      "numeroLegajo": 972023,
      "numeroDocumento": null,
      "nombre": null,
      "apellido": null,
      "malla": "Malla Informática 2015",
      "anioInscripcion": null,
      "codMateria": "312",
      "materia": "Contabilidad",
      "carrera": "Informática",
      "semestre": 4,
      "fechaExamen": "2025-06-24T16:00:00",
      "fechaLimiteInscripcionExamen": "2025-06-22T10:00:00",
      "fechaInscripcionMateria": "2025-02-19T10:38:56.8639985",
      "fechaInscripcion": "2025-06-11T18:09:23.6789929",
      "usuarioInscripcion": null,
      "porcentajeAsistencia": 79,
      "porcentajePP": 74,
      "porcentajePF": 0,
      "porcentajePC": 0,
      "calificacion": null,
      "calificacionText": null,
      "esInconsistente": false,
      "asistenciaMateria": 0,
      "ppMateria": 0,
      "inscripto": true,
      "esRecuperatorio": false,
      "instancia": {
        "value": 0,
        "label": "Final",
        "parentId": 0,
        "item": {
          "asis": true,
          "pp": true,
          "motivo": "PP > 49"
        }
      },
      "estadoExamen": null
    },
    {
      "id": 29759,
      "examenId": 989,
      "usuarioId": 1217,
      "studentId": 1068,
      "numeroLegajo": 972023,
      "numeroDocumento": null,
      "nombre": null,
      "apellido": null,
      "malla": "Malla Informática 2015",
      "anioInscripcion": null,
      "codMateria": "313",
      "materia": "Fundamentos de la Administración",
      "carrera": "Informática",
      "semestre": 4,
      "fechaExamen": "2025-06-19T15:00:00",
      "fechaLimiteInscripcionExamen": "2025-06-17T10:00:00",
      "fechaInscripcionMateria": "2025-02-19T10:38:56.8527161",
      "fechaInscripcion": "0001-01-01T00:00:00",
      "usuarioInscripcion": null,
      "porcentajeAsistencia": 100,
      "porcentajePP": 88,
      "porcentajePF": 0,
      "porcentajePC": 0,
      "calificacion": null,
      "calificacionText": null,
      "esInconsistente": false,
      "asistenciaMateria": 0,
      "ppMateria": 0,
      "inscripto": false,
      "esRecuperatorio": false,
      "instancia": {
        "value": 0,
        "label": "Final",
        "parentId": 0,
        "item": {
          "asis": true,
          "pp": true,
          "motivo": "PP > 49"
        }
      },
      "estadoExamen": null
    },
    {
      "id": 29757,
      "examenId": 981,
      "usuarioId": 1217,
      "studentId": 1068,
      "numeroLegajo": 972023,
      "numeroDocumento": null,
      "nombre": null,
      "apellido": null,
      "malla": "Malla Informática 2015",
      "anioInscripcion": null,
      "codMateria": "017",
      "materia": "Probabilidades y Estadística",
      "carrera": "Informática",
      "semestre": 4,
      "fechaExamen": "2025-06-17T14:00:00",
      "fechaLimiteInscripcionExamen": "2025-06-15T10:00:00",
      "fechaInscripcionMateria": "2025-02-19T10:38:56.8448861",
      "fechaInscripcion": "2025-06-11T16:45:06.5916505",
      "usuarioInscripcion": null,
      "porcentajeAsistencia": 89,
      "porcentajePP": 87,
      "porcentajePF": 0,
      "porcentajePC": 0,
      "calificacion": null,
      "calificacionText": null,
      "esInconsistente": false,
      "asistenciaMateria": 0,
      "ppMateria": 0,
      "inscripto": true,
      "esRecuperatorio": false,
      "instancia": {
        "value": 0,
        "label": "Final",
        "parentId": 0,
        "item": {
          "asis": true,
          "pp": true,
          "motivo": "PP > 49"
        }
      },
      "estadoExamen": null
    }
  ],
  "filters": {
    "nombre": null,
    "apellido": null,
    "codigoMateria": null,
    "materia": null,
    "malla": null,
    "carrera": null,
    "numeroSemestre": null,
    "carreraId": null,
    "periodoId": null,
    "anhoLectivo": null,
    "semestreId": null,
    "materiaId": null
  },
  "pageSize": 25,
  "page": 1,
  "totalItemsCount": 4
}